{
    "基本情報": {
        "data_name": "成績データ",
        "record_length": 376
    },
    "データ位置": {
        "レースキー": {
            "start_bit": 0,
            "end_bit": 7
        },
        "馬番": {
            "start_bit": 8,
            "end_bit": 9
        },
        "競走成績キー_血統登録番号": {
            "start_bit": 10,
            "end_bit": 17
        },
        "競走成績キー_年月日": {
            "start_bit": 18,
            "end_bit": 25
        },
        "馬名": {
            "start_bit": 26,
            "end_bit": 43
        },
        "レース条件_距離": {
            "start_bit": 44,
            "end_bit": 47
        },
        "レース条件_トラック情報_芝ダ障害コード": {
            "start_bit": 48,
            "end_bit": 48
        },
        "レース条件_トラック情報_右左": {
            "start_bit": 49,
            "end_bit": 49
        },
        "レース条件_トラック情報_内外": {
            "start_bit": 50,
            "end_bit": 50
        },
        "レース条件_馬場状態": {
            "start_bit": 51,
            "end_bit": 52
        },
        "レース条件_種別": {
            "start_bit": 53,
            "end_bit": 54
        },
        "レース条件_条件": {
            "start_bit": 55,
            "end_bit": 56
        },
        "レース条件_記号": {
            "start_bit": 57,
            "end_bit": 59
        },
        "レース条件_重量": {
            "start_bit": 60,
            "end_bit": 60
        },
        "レース条件_頭数": {
            "start_bit": 87,
            "end_bit": 88
        },
        "レース条件_レース名略称": {
            "start_bit": 89,
            "end_bit": 92
        },
        "馬成績_着順": {
            "start_bit": 93,
            "end_bit": 94
        },
        "馬成績_異常区分": {
            "start_bit": 95,
            "end_bit": 95
        },
        "馬成績_タイム": {
            "start_bit": 96,
            "end_bit": 99
        },
        "馬成績_斤量": {
            "start_bit": 100,
            "end_bit": 102
        },
        "馬成績_騎手名": {
            "start_bit": 103,
            "end_bit": 108
        },
        "馬成績_調教師名": {
            "start_bit": 109,
            "end_bit": 114
        },
        "馬成績_確定単勝オッズ": {
            "start_bit": 115,
            "end_bit": 120
        },
        "馬成績_確定単勝人気順位": {
            "start_bit": 121,
            "end_bit": 122
        },
        "ＪＲＤＢデータ_ＩＤＭ": {
            "start_bit": 123,
            "end_bit": 125
        },
        "ＪＲＤＢデータ_素点": {
            "start_bit": 126,
            "end_bit": 128
        },
        "ＪＲＤＢデータ_馬場差": {
            "start_bit": 129,
            "end_bit": 131
        },
        "ＪＲＤＢデータ_ペース": {
            "start_bit": 132,
            "end_bit": 134
        },
        "ＪＲＤＢデータ_コース取り": {
            "start_bit": 156,
            "end_bit": 156
        },
        "ＪＲＤＢデータ_上昇度コード": {
            "start_bit": 157,
            "end_bit": 157
        },
        "ＪＲＤＢデータ_クラスコード": {
            "start_bit": 158,
            "end_bit": 159
        },
        "ＪＲＤＢデータ_馬体コード": {
            "start_bit": 160,
            "end_bit": 160
        },
        "ＪＲＤＢデータ_気配コード": {
            "start_bit": 161,
            "end_bit": 161
        },
        "ＪＲＤＢデータ_レースペース": {
            "start_bit": 162,
            "end_bit": 162
        },
        "ＪＲＤＢデータ_馬ペース": {
            "start_bit": 163,
            "end_bit": 163
        },
        "ＪＲＤＢデータ_テン指数": {
            "start_bit": 164,
            "end_bit": 168
        },
        "ＪＲＤＢデータ_上がり指数": {
            "start_bit": 169,
            "end_bit": 173
        },
        "ＪＲＤＢデータ_ペース指数": {
            "start_bit": 174,
            "end_bit": 178
        },
        "ＪＲＤＢデータ_レースＰ指数": {
            "start_bit": 179,
            "end_bit": 183
        },
        "ＪＲＤＢデータ_1(2)着馬名": {
            "start_bit": 184,
            "end_bit": 189
        },
        "ＪＲＤＢデータ_1(2)着タイム差": {
            "start_bit": 190,
            "end_bit": 192
        },
        "ＪＲＤＢデータ_前３Ｆタイム": {
            "start_bit": 193,
            "end_bit": 195
        },
        "ＪＲＤＢデータ_後３Ｆタイム": {
            "start_bit": 196,
            "end_bit": 198
        },
        "ＪＲＤＢデータ_備考": {
            "start_bit": 199,
            "end_bit": 210
        },
        "確定複勝オッズ下": {
            "start_bit": 215,
            "end_bit": 230
        },
        "10時単勝オッズ": {
            "start_bit": 231,
            "end_bit": 236
        },
        "10時複勝オッズ": {
            "start_bit": 237,
            "end_bit": 242
        },
        "騎手コード": {
            "start_bit": 257,
            "end_bit": 261
        },
        "調教師コード": {
            "start_bit": 262,
            "end_bit": 266
        },
        "馬体重": {
            "start_bit": 267,
            "end_bit": 269
        },
        "馬体重増減": {
            "start_bit": 270,
            "end_bit": 272
        },
        "天候コード": {
            "start_bit": 273,
            "end_bit": 273
        },
        "コース": {
            "start_bit": 274,
            "end_bit": 274
        },
        "レース脚質": {
            "start_bit": 275,
            "end_bit": 275
        },
        "払戻データ_単勝": {
            "start_bit": 276,
            "end_bit": 282
        },
        "払戻データ_複勝": {
            "start_bit": 283,
            "end_bit": 289
        },
        "本賞金": {
            "start_bit": 291,
            "end_bit": 294
        },
        "収得賞金": {
            "start_bit": 295,
            "end_bit": 299
        },
        "レースペース流れ": {
            "start_bit": 300,
            "end_bit": 301
        },
        "馬ペース流れ": {
            "start_bit": 302,
            "end_bit": 303
        },
        "４角コース取り": {
            "start_bit": 304,
            "end_bit": 304
        }
    }
}
